autoretouch/.autoretouch-complete.fish
autoretouch/.autoretouch-complete.zsh
autoretouch/__init__.py
autoretouch/api_client/__init__.py
autoretouch/api_client/authenticator.py
autoretouch/api_client/client.py
autoretouch/api_client/model.py
autoretouch/cli/__init__.py
autoretouch/cli/commands.py
autoretouch-0.0.2.dist-info/LICENSE
autoretouch-0.0.2.dist-info/METADATA
autoretouch-0.0.2.dist-info/WHEEL
autoretouch-0.0.2.dist-info/entry_points.txt
autoretouch-0.0.2.dist-info/top_level.txt
autoretouch-0.0.2.dist-info/RECORD
