Metadata-Version: 2.1
Name: autoretouch
Version: 0.0.2
Summary: cli and python package to communicate with the autoRetouch API
Author: ['Antoine Daurat <antoine@autoretouch.com>', 'Oliver Allweyer <oliver@autoretouch.com>', 'Till Lorentzen <till@autoretouch.com>']
License: BSD Zero
License-File: LICENSE
Requires-Dist: requests
Requires-Dist: click (==8.1.3)
Requires-Dist: click-log (==0.4.0)
